jntts/about.py
jntts/box_voice.py
jntts/config.py
jntts/file_tts.py
jntts/hardware_check.py
jntts/main.py
jntts/tts_utils.py
jntts/ui.py
jntts_cli-1.0.3.dist-info/licenses/LICENSE
jntts_cli-1.0.3.dist-info/METADATA
jntts_cli-1.0.3.dist-info/WHEEL
jntts_cli-1.0.3.dist-info/entry_points.txt
jntts_cli-1.0.3.dist-info/top_level.txt
jntts_cli-1.0.3.dist-info/RECORD
