Metadata-Version: 2.4
Name: jntts-cli
Version: 1.0.3
Summary: Một công cụ TTS sử dụng mô hình Bark/Suno để chuyển đổi văn bản thành giọng nói.
Author-email: Justin Nguyen 🇻🇳 <duchuy_1997@hotmail.com>
License: ================================================================================
Classifier: Development Status :: 4 - Beta
Classifier: Programming Language :: Python :: 3
Classifier: Operating System :: OS Independent
Classifier: Topic :: Multimedia :: Sound/Audio :: Speech
Requires-Python: >=3.9
License-File: LICENSE
Requires-Dist: torch
Requires-Dist: transformers
Requires-Dist: sounddevice
Requires-Dist: numpy
Requires-Dist: tqdm
Requires-Dist: pydub
Requires-Dist: pyfiglet
Requires-Dist: psutil
Requires-Dist: pynvml
Requires-Dist: py-cpuinfo
Requires-Dist: appdirs
Dynamic: license-file
